CONTRIBUTING.rst
LICENSE
MANIFEST.in
README.md
setup.py
django_propeller/__init__.py
django_propeller/__init__.pyc
django_propeller/apps.py
django_propeller/apps.pyc
django_propeller/card.py
django_propeller/card.pyc
django_propeller/components.py
django_propeller/components.pyc
django_propeller/enums.pyc
django_propeller/exceptions.py
django_propeller/exceptions.pyc
django_propeller/forms.py
django_propeller/forms.pyc
django_propeller/models.py
django_propeller/models.pyc
django_propeller/navbar.py
django_propeller/navbar.pyc
django_propeller/propeller.py
django_propeller/propeller.pyc
django_propeller/renderers.py
django_propeller/renderers.pyc
django_propeller/test_data.py
django_propeller/test_data.pyc
django_propeller/test_results.py
django_propeller/test_results.pyc
django_propeller/tests.py
django_propeller/tests.pyc
django_propeller/text.py
django_propeller/text.pyc
django_propeller/utils.py
django_propeller/utils.pyc
django_propeller/views.py
django_propeller/views.pyc
django_propeller.egg-info/PKG-INFO
django_propeller.egg-info/SOURCES.txt
django_propeller.egg-info/dependency_links.txt
django_propeller.egg-info/not-zip-safe
django_propeller.egg-info/top_level.txt
django_propeller/__pycache__/__init__.cpython-35.pyc
django_propeller/__pycache__/__init__.cpython-36.pyc
django_propeller/__pycache__/components.cpython-35.pyc
django_propeller/__pycache__/exceptions.cpython-35.pyc
django_propeller/__pycache__/forms.cpython-35.pyc
django_propeller/__pycache__/models.cpython-35.pyc
django_propeller/__pycache__/propeller.cpython-35.pyc
django_propeller/__pycache__/renderers.cpython-35.pyc
django_propeller/__pycache__/tests.cpython-35.pyc
django_propeller/__pycache__/text.cpython-35.pyc
django_propeller/__pycache__/utils.cpython-35.pyc
django_propeller/migrations/__init__.py
django_propeller/migrations/__init__.pyc
django_propeller/migrations/__pycache__/__init__.cpython-35.pyc
django_propeller/static/css/propeller.min.css
django_propeller/static/css/propeller.min.css.map
django_propeller/static/js/propeller.js.map
django_propeller/static/js/propeller.min.js
django_propeller/static/propeller/fonts/roboto/Roboto-Black-webfont.eot
