Metadata-Version: 1.1
Name: django-propeller
Version: 1.5.0
Summary: Propeller support for Django projects
Home-page: https://github.com/dyve/django-propeller
Author: Thorsten Froehlich
Author-email: tfroehlich82@gmx.ch   
License: MIT License
Keywords: django-propeller
Platform: UNKNOWN
Classifier: Development Status :: 4 - Beta
Classifier: Intended Audience :: Developers
Classifier: License :: OSI Approved :: Apache Software License
Classifier: Programming Language :: Python :: 2
Classifier: Programming Language :: Python :: 2.7
Classifier: Programming Language :: Python :: 3
Classifier: Programming Language :: Python :: 3.3
Classifier: Programming Language :: Python :: 3.4
Classifier: Programming Language :: Python :: 3.5
Classifier: Operating System :: OS Independent
Classifier: Topic :: Software Development :: Libraries
Classifier: Topic :: Utilities
Classifier: Environment :: Web Environment
Classifier: Framework :: Django
